rekall_lib/__init__.py
rekall_lib/crypto.py
rekall_lib/registry.py
rekall_lib/serializer.py
rekall_lib/serializer_test.py
rekall_lib/testlib.py
rekall_lib/utils.py
rekall_lib/yaml_utils.py
rekall_lib/types/__init__.py
rekall_lib/types/actions.py
rekall_lib/types/agent.py
rekall_lib/types/artifacts.py
rekall_lib/types/client.py
rekall_lib/types/collections.py
rekall_lib/types/location.py
rekall_lib/types/resources.py
rekall_lib-1.7.0rc1.dist-info/DESCRIPTION.rst
rekall_lib-1.7.0rc1.dist-info/METADATA
rekall_lib-1.7.0rc1.dist-info/RECORD
rekall_lib-1.7.0rc1.dist-info/WHEEL
rekall_lib-1.7.0rc1.dist-info/entry_points.txt
rekall_lib-1.7.0rc1.dist-info/metadata.json
rekall_lib-1.7.0rc1.dist-info/top_level.txt
