Metadata-Version: 2.0
Name: rekall-lib
Version: 1.7.0rc1
Summary: Rekall Support Libraries
Home-page: https://www.rekall-forensic.com/
Author: The Rekall team
Author-email: rekall-discuss@googlegroups.com
License: GPL
Platform: UNKNOWN
Classifier: Development Status :: 4 - Beta
Classifier: Environment :: Console
Classifier: Operating System :: OS Independent
Classifier: Programming Language :: Python
Requires-Dist: arrow (==0.7.0)
Requires-Dist: sortedcontainers (==1.4.4)
